odoo/addons/pos_cash_move_reason/README.rst
odoo/addons/pos_cash_move_reason/__init__.py
odoo/addons/pos_cash_move_reason/__manifest__.py
odoo/addons/pos_cash_move_reason/demo/account_account.xml
odoo/addons/pos_cash_move_reason/demo/pos_move_reason.xml
odoo/addons/pos_cash_move_reason/i18n/ar.po
odoo/addons/pos_cash_move_reason/i18n/bg.po
odoo/addons/pos_cash_move_reason/i18n/bs.po
odoo/addons/pos_cash_move_reason/i18n/ca.po
odoo/addons/pos_cash_move_reason/i18n/ca_ES.po
odoo/addons/pos_cash_move_reason/i18n/cs.po
odoo/addons/pos_cash_move_reason/i18n/da.po
odoo/addons/pos_cash_move_reason/i18n/de.po
odoo/addons/pos_cash_move_reason/i18n/el_GR.po
odoo/addons/pos_cash_move_reason/i18n/en_GB.po
odoo/addons/pos_cash_move_reason/i18n/es.po
odoo/addons/pos_cash_move_reason/i18n/es_AR.po
odoo/addons/pos_cash_move_reason/i18n/es_CL.po
odoo/addons/pos_cash_move_reason/i18n/es_CO.po
odoo/addons/pos_cash_move_reason/i18n/es_CR.po
odoo/addons/pos_cash_move_reason/i18n/es_DO.po
odoo/addons/pos_cash_move_reason/i18n/es_EC.po
odoo/addons/pos_cash_move_reason/i18n/es_MX.po
odoo/addons/pos_cash_move_reason/i18n/es_PE.po
odoo/addons/pos_cash_move_reason/i18n/es_PY.po
odoo/addons/pos_cash_move_reason/i18n/es_VE.po
odoo/addons/pos_cash_move_reason/i18n/et.po
odoo/addons/pos_cash_move_reason/i18n/eu.po
odoo/addons/pos_cash_move_reason/i18n/fa.po
odoo/addons/pos_cash_move_reason/i18n/fi.po
odoo/addons/pos_cash_move_reason/i18n/fr.po
odoo/addons/pos_cash_move_reason/i18n/fr_CA.po
odoo/addons/pos_cash_move_reason/i18n/fr_CH.po
odoo/addons/pos_cash_move_reason/i18n/gl.po
odoo/addons/pos_cash_move_reason/i18n/he.po
odoo/addons/pos_cash_move_reason/i18n/hr.po
odoo/addons/pos_cash_move_reason/i18n/hr_HR.po
odoo/addons/pos_cash_move_reason/i18n/hu.po
odoo/addons/pos_cash_move_reason/i18n/id.po
odoo/addons/pos_cash_move_reason/i18n/it.po
odoo/addons/pos_cash_move_reason/i18n/ja.po
odoo/addons/pos_cash_move_reason/i18n/ko.po
odoo/addons/pos_cash_move_reason/i18n/lt.po
odoo12_addon_pos_cash_move_reason-12.0.3.2.1.dist-info/METADATA
odoo12_addon_pos_cash_move_reason-12.0.3.2.1.dist-info/WHEEL
odoo12_addon_pos_cash_move_reason-12.0.3.2.1.dist-info/top_level.txt
odoo12_addon_pos_cash_move_reason-12.0.3.2.1.dist-info/RECORD
